modo_code/__init__.py
modo_code/app/__init__.py
modo_code/app/app.py
modo_code/app/local_handler.py
modo_code/app/server_interface.py
modo_code/graph_construction/__init__.py
modo_code/graph_construction/core/__init__.py
modo_code/graph_construction/core/graph_builder.py
modo_code/graph_construction/languages/Parsers.py
modo_code/graph_construction/languages/__init__.py
modo_code/graph_construction/languages/base_alias_extractor.py
modo_code/graph_construction/languages/base_parser.py
modo_code/graph_construction/languages/dart/__init__.py
modo_code/graph_construction/languages/dart/dart_parser.py
modo_code/graph_construction/languages/javascript/__init__.py
modo_code/graph_construction/languages/javascript/javascript_parser.py
modo_code/graph_construction/languages/javascript/jsx_parser.py
modo_code/graph_construction/languages/python/__init__.py
modo_code/graph_construction/languages/python/python_parser.py
modo_code/graph_construction/languages/ruby/__init__.py
modo_code/graph_construction/languages/ruby/ruby_parser.py
modo_code/graph_construction/languages/typescript/__init__.py
modo_code/graph_construction/languages/typescript/tsx_parser.py
modo_code/graph_construction/languages/typescript/typescript_parser.py
modo_code/graph_construction/utils/__init__.py
modo_code/graph_construction/utils/format_nodes.py
modo_code/graph_construction/utils/interfaces/GlobalGraphInfo.py
modo_code/graph_construction/utils/interfaces/__init__.py
modo_code/main.py
modo_code-0.2.6.dist-info/METADATA
modo_code-0.2.6.dist-info/WHEEL
modo_code-0.2.6.dist-info/entry_points.txt
modo_code-0.2.6.dist-info/RECORD
